{
    "display": {
      "icon": {
        "id": "minecraft:diamond_chestplate"
      },
      "title": "Enhanced Strength!!",
      "description": "Get a Durable Item, your armor is much stronger! But you are slower now too, so like, have fun!!",
      "frame": "task"
    },
    "parent": "fluffytg:enchantmentroot",
    "criteria": {
      "getHermes": {
        "trigger": "minecraft:inventory_changed",
        "conditions": {
          "items": [
            {
              "predicates": {
                "minecraft:enchantments": [
                  {
                    "enchantments": "fluffytg:durable",
                    "levels": {
                      "min": 1
                    }
                  }
                ]
              }
            }
          ]
        }
      }
    }
  }
  