{
  "pools": [
    {
      "rolls": 8,
      "entries": [
        {
          "type": "minecraft:item",
          "name": "minecraft:cobblestone",
          "weight": 18,
          "functions": [
            {
              "function": "minecraft:set_count",
              "count": {
                "min": 6,
                "max": 32
              }
            }
          ]
        },
        {
          "type": "minecraft:item",
          "name": "minecraft:mossy_cobblestone",
          "weight": 16,
          "functions": [
            {
              "function": "minecraft:set_count",
              "count": {
                "min": 4,
                "max": 8
              }
            }
          ]
        },
        {
          "type": "minecraft:item",
          "name": "minecraft:bread",
          "weight": 15,
          "functions": [
            {
              "function": "minecraft:set_count",
              "count": {
                "min": 3,
                "max": 7
              }
            }
          ]
        },
        {
          "type": "minecraft:item",
          "name": "minecraft:pumpkin_pie",
          "weight": 15,
          "functions": [
            {
              "function": "minecraft:set_count",
              "count": {
                "min": 3,
                "max": 9
              }
            }
          ]
        },
        {
          "type": "minecraft:item",
          "name": "minecraft:tipped_arrow",
          "weight": 14,
          "functions": [
            {
              "function": "minecraft:set_count",
              "count": {
                "min": 1,
                "max": 3
              }
            },
            {
              "function": "minecraft:set_potion",
              "id": "minecraft:healing"
            }
          ]
        },
        {
          "type": "minecraft:item",
          "name": "minecraft:chain",
          "weight": 12,
          "functions": [
            {
              "function": "minecraft:set_count",
              "count": {
                "min": 1,
                "max": 3
              }
            }
          ]
        },
        {
          "type": "minecraft:item",
          "name": "minecraft:lantern",
          "weight": 10,
          "functions": [
            {
              "function": "minecraft:set_count",
              "count": {
                "min": 3,
                "max": 6
              }
            }
          ]
        },
        {
          "type": "minecraft:item",
          "name": "minecraft:raw_iron",
          "weight": 10,
          "functions": [
            {
              "function": "minecraft:set_count",
              "count": {
                "min": 2,
                "max": 8
              }
            }
          ]
        },
        {
          "type": "minecraft:item",
          "name": "minecraft:splash_potion",
          "weight": 5,
          "functions": [
            {
              "function": "minecraft:set_components",
              "components": {
                "minecraft:max_stack_size": 8
              }
            },
            {
              "function": "minecraft:set_potion",
              "id": "minecraft:healing"
            }
          ]
        }
      ]
    },
    {
      "rolls": 1,
      "entries": [
        {
          "type": "minecraft:item",
          "name": "minecraft:diamond",
          "weight": 1
        },
        {
          "type": "minecraft:item",
          "name": "minecraft:ominous_bottle",
          "weight": 2,
          "functions": [
            {
              "function": "minecraft:set_ominous_bottle_amplifier",
              "amplifier": {
                "min": 0,
                "max": 3
              }
            }
          ]
        },
        {
          "type": "minecraft:item",
          "name": "minecraft:iron_boots",
          "weight": 3,
          "functions": [
            {
              "function": "minecraft:set_enchantments",
              "enchantments": {
                "fluffytg:hermes": 1
              }
            },
            {
              "function": "minecraft:set_components",
              "components": {
                "minecraft:trim": {
                  "material": "minecraft:copper",
                  "pattern": "minecraft:bolt"
                }
              }
            },
            {
              "function": "minecraft:enchant_randomly",
              "options": "#minecraft:on_random_loot"
            }
          ]
        },
        {
          "type": "minecraft:item",
          "name": "minecraft:potion",
          "weight": 2,
          "functions": [
            {
              "function": "minecraft:set_components",
              "components": {
                "minecraft:max_stack_size": 8
              }
            },
            {
              "function": "minecraft:set_potion",
              "id": "minecraft:slow_falling"
            }
          ]
        }
      ]
    }
  ]
}
